bioezy/__init__.py
bioezy/bzy.py
bioezy-0.0.6.dist-info/LICENSE
bioezy-0.0.6.dist-info/METADATA
bioezy-0.0.6.dist-info/WHEEL
bioezy-0.0.6.dist-info/top_level.txt
bioezy-0.0.6.dist-info/RECORD
